.coveragerc
.gitignore
.travis.yml
CHANGES.rst
LICENSE.rst
MANIFEST.in
README.rst
requirements.txt
setup.py
examples/library.py
examples/metadata.py
plex.metadata.py.egg-info/PKG-INFO
plex.metadata.py.egg-info/SOURCES.txt
plex.metadata.py.egg-info/dependency_links.txt
plex.metadata.py.egg-info/requires.txt
plex.metadata.py.egg-info/top_level.txt
plex_metadata/__init__.py
plex_metadata/guid.py
plex_metadata/library.py
plex_metadata/matcher.py
plex_metadata/metadata.py
plex_metadata/core/__init__.py
plex_metadata/core/defaults.py
plex_metadata/core/helpers.py
tests/__init__.py
tests/test_guid.py
tests/test_matcher.py
tests/core/__init__.py
tests/core/helpers.py