Metadata-Version: 1.1
Name: plex.metadata.py
Version: 0.7.1
Summary: Metadata extension for plex.py
Home-page: https://github.com/fuzeman/plex.metadata.py
Author: Dean Gardiner
Author-email: me@dgardiner.net
License: MIT
Platform: any
Classifier: Development Status :: 4 - Beta
Classifier: Intended Audience :: Developers
Classifier: Operating System :: OS Independent
Classifier: Programming Language :: Python
